firebasedata/__init__.py
firebasedata/data.py
firebasedata/live.py
firebasedata/watcher.py
FirebaseData-0.6.1.dist-info/LICENSE
FirebaseData-0.6.1.dist-info/METADATA
FirebaseData-0.6.1.dist-info/WHEEL
FirebaseData-0.6.1.dist-info/top_level.txt
FirebaseData-0.6.1.dist-info/RECORD
