Metadata-Version: 1.2
Name: FirebaseData
Version: 0.6.1
Summary: Utilities for storing, retrieving, and monitoring Firebase Realtime Database objects in Python.
Home-page: https://github.com/heston/firebase-live-data
Author: Heston Liebowitz
License: MIT
Platform: UNKNOWN
Requires-Python: >=3, <4
